awsume_1password_plugin/1password.py
awsume_1password_plugin/__init__.py
awsume_1password_plugin/helpers/__init__.py
awsume_1password_plugin/helpers/config.py
awsume_1password_plugin/helpers/opCLI.py
awsume_1password_plugin/helpers/profile.py
awsume_1password_plugin_simosca-1.0.8.dist-info/licenses/LICENSE
awsume_1password_plugin_simosca-1.0.8.dist-info/METADATA
awsume_1password_plugin_simosca-1.0.8.dist-info/WHEEL
awsume_1password_plugin_simosca-1.0.8.dist-info/entry_points.txt
awsume_1password_plugin_simosca-1.0.8.dist-info/top_level.txt
awsume_1password_plugin_simosca-1.0.8.dist-info/RECORD
